event_bridge_log_shared/__init__.py
event_bridge_log_shared/_version.py
event_bridge_log_shared/models/__init__.py
event_bridge_log_shared/models/events/__init__.py
event_bridge_log_shared/models/events/analytics.py
event_bridge_log_shared/models/events/base.py
event_bridge_log_shared/models/events/ecommerce.py
event_bridge_log_shared/models/events/inventory.py
event_bridge_log_shared/models/events/payment.py
event_bridge_log_shared/models/events/user.py
event_bridge_log_shared/utils/__init__.py
event_bridge_log_shared/utils/config.py
event_bridge_log_shared-1.0.4.dist-info/METADATA
event_bridge_log_shared-1.0.4.dist-info/WHEEL
event_bridge_log_shared-1.0.4.dist-info/licenses/LICENSE
event_bridge_log_shared-1.0.4.dist-info/RECORD
