Metadata-Version: 2.4
Name: event-bridge-log-shared
Version: 1.0.4
Summary: Shared models and utilities for Event Bridge Log Analytics Platform
Project-URL: Homepage, https://github.com/cblack2008/event-bridge-log-shared
Project-URL: Repository, https://github.com/cblack2008/event-bridge-log-shared
Project-URL: Documentation, https://cblack2008.github.io/event-bridge-log-shared
Project-URL: Issues, https://github.com/cblack2008/event-bridge-log-shared/issues
Project-URL: Changelog, https://github.com/cblack2008/event-bridge-log-shared/blob/main/CHANGELOG.md
Author: cblack2008
License: MIT License
License-File: LICENSE
Keywords: analytics,aws,eventbridge,microservices,shared
Classifier: Development Status :: 4 - Beta
Classifier: Intended Audience :: Developers
Classifier: License :: OSI Approved :: MIT License
Classifier: Programming Language :: Python :: 3
Classifier: Programming Language :: Python :: 3.13
Classifier: Topic :: Software Development :: Libraries :: Python Modules
Classifier: Topic :: System :: Monitoring
Requires-Python: >=3.13
Requires-Dist: boto3<2.0.0,>=1.40.0
Requires-Dist: botocore<2.0.0,>=1.40.0
Requires-Dist: build>=1.3.0
Requires-Dist: pydantic-settings<3.0.0,>=2.10.0
Requires-Dist: pydantic<3.0.0,>=2.11.0
Requires-Dist: python-dateutil<3.0.0,>=2.8.0
Requires-Dist: python-dotenv<2.0.0,>=1.0.0
Requires-Dist: structlog<24.0.0,>=23.0.0
Requires-Dist: twine>=6.1.0
Provides-Extra: dev
Requires-Dist: black<26.0.0,>=25.1.0; extra == 'dev'
Requires-Dist: mkdocs-material<10.0.0,>=9.0.0; extra == 'dev'
Requires-Dist: mkdocs<2.0.0,>=1.5.0; extra == 'dev'
Requires-Dist: mypy<2.0.0,>=1.7.0; extra == 'dev'
Requires-Dist: pre-commit<4.0.0,>=3.7.0; extra == 'dev'
Requires-Dist: pytest-asyncio<1.0.0,>=0.21.0; extra == 'dev'
Requires-Dist: pytest-cov<5.0.0,>=4.1.0; extra == 'dev'
Requires-Dist: pytest-mock<4.0.0,>=3.12.0; extra == 'dev'
Requires-Dist: pytest<8.0.0,>=7.4.0; extra == 'dev'
Requires-Dist: ruff<1.0.0,>=0.12.8; extra == 'dev'
